i3tools-0.2.0.dist-info/METADATA
i3tools-0.2.0.dist-info/WHEEL
i3tools-0.2.0.dist-info/entry_points.txt
i3tools/__init__.py
i3tools/_message.py
i3tools/ws.py
i3tools-0.2.0.dist-info/RECORD
