Metadata-Version: 2.1
Name: i3tools
Version: 0.2.0
Summary: Tools for i3wm
Keywords: i3wm
Author-Email: David Delassus <david.jose.delassus@gmail.com>
License: MIT
Classifier: Development Status :: 5 - Production/Stable
Classifier: License :: OSI Approved :: MIT License
Classifier: Operating System :: Unix
Classifier: Operating System :: POSIX :: Linux
Classifier: Topic :: Utilities
Classifier: Topic :: Desktop Environment
Classifier: Intended Audience :: End Users/Desktop
Classifier: Programming Language :: Python
Classifier: Programming Language :: Python :: 3
Classifier: Programming Language :: Python :: Implementation :: CPython
Project-URL: homepage, https://github.com/linkdd/i3tools
Requires-Python: >=3.13
